biz_monitor/__init__.py
biz_monitor/biz_logging/__init__.py
biz_monitor/biz_logging/async_log.py
biz_monitor/biz_logging/log.py
biz_monitor/biz_metrics/__init__.py
biz_monitor/biz_tracing/__init__.py
biz_monitor/biz_tracing/tracer.py
biz_monitor/biz_tracing/aiohttp_opentracing/__init__.py
biz_monitor/biz_tracing/aiohttp_opentracing/client_tracer.py
biz_monitor/biz_tracing/aiohttp_opentracing/middlewares.py
biz_monitor/biz_tracing/flask_opentracing/__init__.py
biz_monitor/biz_tracing/flask_opentracing/tracing.py
biz_monitor/biz_tracing/requests_opentracing/__init__.py
biz_monitor/biz_tracing/requests_opentracing/tracing.py
biz_monitor/biz_tracing/tornado_opentracing/__init__.py
biz_monitor/biz_tracing/tornado_opentracing/_constants.py
biz_monitor/biz_tracing/tornado_opentracing/application.py
biz_monitor/biz_tracing/tornado_opentracing/handlers.py
biz_monitor/biz_tracing/tornado_opentracing/httpclient.py
biz_monitor/biz_tracing/tornado_opentracing/initialization.py
biz_monitor/biz_tracing/tornado_opentracing/tornado_scope.py
biz_monitor/biz_tracing/tornado_opentracing/tracing.py
biz_monitor-0.5.0.dist-info/METADATA
biz_monitor-0.5.0.dist-info/WHEEL
biz_monitor-0.5.0.dist-info/top_level.txt
biz_monitor-0.5.0.dist-info/RECORD
